cocopp/__init__.py
cocopp/__main__.py
cocopp/_version.py
cocopp/algportfolio.py
cocopp/archiving.py
cocopp/bbob-benchmarkinfos.txt
cocopp/bbob-benchmarkshortinfos.txt
cocopp/bbob-biobj-benchmarkinfos.txt
cocopp/bbob-biobj-benchmarkshortinfos.txt
cocopp/bbob-biobj-ext-benchmarkinfos.txt
cocopp/bbob-biobj-ext-benchmarkshortinfos.txt
cocopp/bbob-constrained-benchmarkinfos.txt
cocopp/bbob-constrained-benchmarkshortinfos.txt
cocopp/bbob-largescale-benchmarkinfos.txt
cocopp/bbob-largescale-benchmarkshortinfos.txt
cocopp/bbob-noisy-benchmarkinfos.txt
cocopp/bbob-noisy-benchmarkshortinfos.txt
cocopp/bestalg.py
cocopp/bestalgentries2009.pickle.gz
cocopp/bwsettings.py
cocopp/captions.py
cocopp/cococommands.py
cocopp/config.py
cocopp/dataformatsettings.py
cocopp/findfiles.py
cocopp/firstsession.py
cocopp/genericsettings.py
cocopp/grayscalesettings.py
cocopp/htmldesc.py
cocopp/latex_commands_for_html.html
cocopp/old_line_styles.py
cocopp/ppconverrorbars.py
cocopp/ppfig.py
cocopp/ppfigcons1.py
cocopp/ppfigdim.py
cocopp/ppfigparam.py
cocopp/pplogloss.py
cocopp/pprldistr.py
cocopp/pprldistr2009_1e-8.pickle.gz
cocopp/pprldistr2009_hardestRLB.pickle.gz
cocopp/pprldistr2009_hardestRLB.py
cocopp/pprldistrever_1e-8.pickle.gz
cocopp/pproc.py
cocopp/ppsingle.py
cocopp/pptable.py
cocopp/pptex.py
cocopp/preparehtml.py
cocopp/preparetexforhtml.py
cocopp/readalign.py
cocopp/rungeneric.py
cocopp/rungeneric1.py
cocopp/rungenericmany.py
cocopp/sanitycheck.py
cocopp/test.py
cocopp/testbedsettings.py
cocopp/toolsdivers.py
cocopp/toolsstats.py
cocopp/comp2/__init__.py
cocopp/comp2/ppfig2.py
cocopp/comp2/pprldistr2.py
cocopp/comp2/ppscatter.py
cocopp/compall/__init__.py
cocopp/compall/organizeRTDpictures.py
cocopp/compall/ppfigcons.py
cocopp/compall/ppfigs.py
cocopp/compall/ppperfprof.py
cocopp/compall/pprldmany.py
cocopp/compall/pptables.py
cocopp/js/sorttable.js
cocopp/refalgs/best09-16-bbob-noisy.tar.gz
cocopp/refalgs/best09-16-bbob.tar.gz
cocopp/refalgs/best2009-bbob-noisy.tar.gz
cocopp-2.6.4.dist-info/METADATA
cocopp-2.6.4.dist-info/WHEEL
cocopp-2.6.4.dist-info/top_level.txt
cocopp-2.6.4.dist-info/RECORD
