Metadata-Version: 2.1
Name: cocopp
Version: 2.6.4
Summary: Benchmarking framework for all types of black-box optimization algorithms, postprocessing.
Author: Raymond Ros, Dejan Tusar
Author-email: Dimo Brockhoff <dimo.brockhoff@inria.fr>, Nikolaus Hansen <nikolaus.hansen@inria.fr>
License: BSD-3-Clause
Project-URL: Homepage, https://numbbo.github.io
Project-URL: Issues, https://github.com/numbbo/coco/issues
Project-URL: Repository, https://github.com/numbbo/coco
Classifier: Development Status :: 4 - Beta
Classifier: Environment :: Console
Classifier: Framework :: IPython
Classifier: Framework :: Jupyter
Classifier: Intended Audience :: Education
Classifier: Intended Audience :: Other Audience
Classifier: Intended Audience :: Science/Research
Classifier: License :: OSI Approved :: BSD License
Classifier: Operating System :: OS Independent
Classifier: Programming Language :: Python :: 3
Classifier: Topic :: Scientific/Engineering :: Artificial Intelligence
Classifier: Topic :: Scientific/Engineering :: Mathematics
Classifier: Topic :: Scientific/Engineering
Requires-Python: >=3.7
Requires-Dist: matplotlib>=3.5.0
Requires-Dist: numpy>=1.21.0
Requires-Dist: platformdirs>=3.8.1
